safety_gridworlds_gymnasium/__init__.py
safety_gridworlds_gymnasium/environments/__init__.py
safety_gridworlds_gymnasium/environments/draw.py
safety_gridworlds_gymnasium/environments/base/__init__.py
safety_gridworlds_gymnasium/environments/base/common.py
safety_gridworlds_gymnasium/environments/base/env.py
safety_gridworlds_gymnasium/environments/base/renderer.py
safety_gridworlds_gymnasium/environments/conveyor_belt/__init__.py
safety_gridworlds_gymnasium/environments/conveyor_belt/common.py
safety_gridworlds_gymnasium/environments/conveyor_belt/env.py
safety_gridworlds_gymnasium/environments/conveyor_belt/renderer.py
safety_gridworlds_gymnasium/environments/island_navigation/__init__.py
safety_gridworlds_gymnasium/environments/island_navigation/common.py
safety_gridworlds_gymnasium/environments/island_navigation/env.py
safety_gridworlds_gymnasium/environments/island_navigation/renderer.py
safety_gridworlds_gymnasium/environments/sokoban/__init__.py
safety_gridworlds_gymnasium/environments/sokoban/common.py
safety_gridworlds_gymnasium/environments/sokoban/env.py
safety_gridworlds_gymnasium/environments/sokoban/renderer.py
safety_gridworlds_gymnasium-2.0.4.dist-info/licenses/LICENSE
safety_gridworlds_gymnasium-2.0.4.dist-info/METADATA
safety_gridworlds_gymnasium-2.0.4.dist-info/WHEEL
safety_gridworlds_gymnasium-2.0.4.dist-info/top_level.txt
safety_gridworlds_gymnasium-2.0.4.dist-info/RECORD
