Metadata-Version: 2.4
Name: safety-gridworlds-gymnasium
Version: 2.0.4
Summary: Safety Gridworlds from Gymnasium
Requires-Python: >=3.11
License-File: LICENSE
Requires-Dist: gymnasium[other]>=1.1.1
Requires-Dist: ipykernel>=6.29.5
Requires-Dist: ipywidgets>=8.1.5
Requires-Dist: numpy>=2.2.4
Requires-Dist: pygame>=2.6.1
Dynamic: license-file
